Metadata-Version: 2.1
Name: utranslate
Version: 1.0.0
Summary: translation module 
Home-page: UNKNOWN
Author: Vaibhav Mankar
Author-email: mankarvaibhav819@gmail.com
License: MIT
Keywords: python
Platform: UNKNOWN
License-File: LICENSE.txt
